zeebee_ai_client/__init__.py
zeebee_ai_client/agents.py
zeebee_ai_client/client.py
zeebee_ai_client/exceptions.py
zeebee_ai_client/layout.py
zeebee_ai_client/pipelines.py
zeebee_ai_client/routing.py
zeebee_ai_client/voice_chat.py
zeebee_ai_client-0.1.6.dist-info/licenses/LICENSE
zeebee_ai_client-0.1.6.dist-info/METADATA
zeebee_ai_client-0.1.6.dist-info/WHEEL
zeebee_ai_client-0.1.6.dist-info/top_level.txt
zeebee_ai_client-0.1.6.dist-info/RECORD
